{
  "image": [{}],
  "dataset": [
    {"name": "cub200"}
  ],
  "batch_design": [
    {"name": "grouped", "group_size": 4, "batch_size": 64},
  ],
  "model": [{"name": "resnet50", "dimension": 128}],
  "loss": [
    {"name": "logistic", "alpha": 1.0},
    {"name": "logistic", "alpha": 2.0},
    {"name": "logistic", "alpha": 4.0},
    {"name": "logistic", "alpha": 8.0}
  ],
  "metrics": [{}],
  "trainer": [
    {"learning_rate": 0.0001, "lr_dimemsion": 0.0001, "lr_decay_steps": 100, "lr_decay_rate": 0.9, "num_epochs": 20},
    {"learning_rate": 0.0003, "lr_dimemsion": 0.0003, "lr_decay_steps": 100, "lr_decay_rate": 0.9, "num_epochs": 20},
    {"learning_rate": 0.00003, "lr_dimemsion": 0.00003, "lr_decay_steps": 100, "lr_decay_rate": 0.9, "num_epochs": 20}
  ]
}
